quick_batch/__init__.py
quick_batch/main.py
quick_batch/manual_scaler.py
quick_batch/processor_app/processor_app/__init__.py
quick_batch/processor_app/processor_app/activate_process.py
quick_batch/processor_app/processor_app/api_connects.py
quick_batch/processor_app/processor_app/run.py
quick_batch/processor_app/wait-for-it.sh
quick_batch/queue_app/Dockerfile
quick_batch/queue_app/queue_app/__init__.py
quick_batch/queue_app/queue_app/apis.py
quick_batch/queue_app/queue_app/queues_init.py
quick_batch/queue_app/queue_app/run.py
quick_batch/queue_app/requirements.txt
quick_batch/queue_app/wait-for-it.sh
quick_batch/runner.py
quick_batch/utilities/__init__.py
quick_batch/utilities/manage_client.py
quick_batch/utilities/manage_containers.py
quick_batch/utilities/manage_dockerfile.py
quick_batch/utilities/manage_images.py
quick_batch/utilities/manage_loggers.py
quick_batch/utilities/manage_networks.py
quick_batch/utilities/manage_queue.py
quick_batch/utilities/manage_requirements.py
quick_batch/utilities/manage_services.py
quick_batch/utilities/manage_setup.py
quick_batch/utilities/manage_swarm.py
quick_batch/utilities/param_checks.py
quick_batch-0.1.13.dist-info/METADATA
quick_batch-0.1.13.dist-info/WHEEL
quick_batch-0.1.13.dist-info/entry_points.txt
quick_batch-0.1.13.dist-info/RECORD
