Metadata-Version: 2.1
Name: quick-batch
Version: 0.1.13
Summary: ultra simple command line tool for docker-scaling batch processing
Home-page: https://github.com/jermwatt/quick_batch
License: MIT
Author: Jeremy Watt
Author-email: jermwatt@gmail.com
Requires-Python: >=3.9,<4.0
Classifier: License :: OSI Approved :: MIT License
Classifier: Programming Language :: Python :: 3
Classifier: Programming Language :: Python :: 3.9
Classifier: Programming Language :: Python :: 3.10
Classifier: Programming Language :: Python :: 3.11
Requires-Dist: docker (>=6.1.2,<7.0.0)
Requires-Dist: fire (>=0.5.0,<0.6.0)
Requires-Dist: pyyaml (<5.5)
